{"id": "sm2-21", "name": "Alolan Vulpix", "flavorText": "It exhales air colder than -58 degrees Fahrenheit. Elderly people in Alola call this Pok\u00e9mon by an older name\u2014Keokeo.", "types": ["Water"], "supertype": "Pok\u00e9mon", "subtypes": ["Basic"], "hp": "60", "evolvesTo": ["Ninetales"], "attacks": [{"name": "Beacon", "cost": [], "convertedEnergyCost": 0, "damage": "", "text": "Search your deck for up to 2 Pok\u00e9mon, reveal them, and put them into your hand. Then, shuffle your deck."}, {"name": "Icy Snow", "cost": ["Colorless", "Colorless"], "convertedEnergyCost": 2, "damage": "20", "text": ""}], "weaknesses": [{"type": "Metal", "value": "\u00d72"}], "retreatCost": ["Colorless"], "convertedRetreatCost": 1, "number": "21", "artist": "You Iribi", "rarity": "Common", "nationalPokedexNumbers": [37], "images": {"small": "https://images.pokemontcg.io/sm2/21.png", "large": "https://images.pokemontcg.io/sm2/21_hires.png"}}