{"id": "bwp-BW16", "name": "Axew", "flavorText": "They use their tusks to crush the berries they eat. Repeated regrowth makes their tusks strong and sharp.", "types": ["Colorless"], "supertype": "Pok\u00e9mon", "subtypes": ["Basic"], "hp": "50", "evolvesTo": ["Fraxure"], "attacks": [{"name": "Dragon Rage", "cost": ["Colorless", "Colorless"], "convertedEnergyCost": 2, "damage": "50", "text": "Flip 2 coins. If either of them is tails, this attack does nothing."}], "retreatCost": ["Colorless"], "convertedRetreatCost": 1, "number": "BW16", "artist": "Masakazu Fukuda", "rarity": "Promo", "nationalPokedexNumbers": [610], "images": {"small": "https://images.pokemontcg.io/bwp/BW16.png", "large": "https://images.pokemontcg.io/bwp/BW16_hires.png"}}