{"id": "bw1-89", "name": "Cinccino", "flavorText": "Their white fur is coated in a special oil that makes it easy for them to deflect attacks.", "types": ["Colorless"], "supertype": "Pok\u00e9mon", "subtypes": ["Stage 1"], "hp": "90", "evolvesFrom": "Minccino", "attacks": [{"name": "Tail Slap", "cost": ["Colorless"], "convertedEnergyCost": 1, "damage": "20\u00d7", "text": "Flip 2 coins. This attack does 20 damage times the number of heads."}, {"name": "Do the Wave", "cost": ["Colorless", "Colorless"], "convertedEnergyCost": 2, "damage": "20\u00d7", "text": "Does 20 damage times the number of your Benched Pok\u00e9mon."}], "weaknesses": [{"type": "Fighting", "value": "\u00d72"}], "retreatCost": ["Colorless"], "convertedRetreatCost": 1, "number": "89", "artist": "Kagemaru Himeno", "rarity": "Rare", "nationalPokedexNumbers": [573], "images": {"small": "https://images.pokemontcg.io/bw1/89.png", "large": "https://images.pokemontcg.io/bw1/89_hires.png"}}