{"id": "swsh3-53", "name": "Dracovish", "flavorText": "Powerful legs and jaws made it the apex predator of its time. Its own overhunting of its prey was what drove it to extinction.", "types": ["Water"], "supertype": "Pok\u00e9mon", "subtypes": ["Stage 1"], "hp": "150", "evolvesFrom": "Rare Fossil", "abilities": [{"name": "Primal Law", "text": "As long as this Pok\u00e9mon is in the Active Spot, your opponent can't play any Pok\u00e9mon from their hand to evolve their Pok\u00e9mon.", "type": "Ability"}], "attacks": [{"name": "Hammer In", "cost": ["Water", "Colorless", "Colorless"], "convertedEnergyCost": 3, "damage": "120", "text": ""}], "weaknesses": [{"type": "Lightning", "value": "\u00d72"}], "retreatCost": ["Colorless", "Colorless", "Colorless"], "convertedRetreatCost": 3, "number": "53", "artist": "Hitoshi Ariga", "rarity": "Rare Holo", "nationalPokedexNumbers": [882], "regulationMark": "D", "images": {"small": "https://images.pokemontcg.io/swsh3/53.png", "large": "https://images.pokemontcg.io/swsh3/53_hires.png"}}