{"id": "swshp-SWSH008", "name": "Galarian Perrserker", "flavorText": "What appears to be an iron helmet is actually hardened hair. This Pok\u00e9mon lives for the thrill of battle.", "types": ["Metal"], "supertype": "Pok\u00e9mon", "subtypes": ["Stage 1"], "hp": "120", "evolvesFrom": "Galarian Meowth", "abilities": [{"name": "Steely Spirit", "text": "Your Metal Pok\u00e9mon's attacks do 20 more damage to your opponent's Active Pok\u00e9mon (before applying Weakness and Resistance).", "type": "Ability"}], "attacks": [{"name": "Metal Claw", "cost": ["Metal", "Metal", "Colorless"], "convertedEnergyCost": 3, "damage": "70", "text": ""}], "weaknesses": [{"type": "Fire", "value": "\u00d72"}], "resistances": [{"type": "Grass", "value": "-30"}], "retreatCost": ["Colorless", "Colorless"], "convertedRetreatCost": 2, "number": "SWSH008", "artist": "Akira Komayama", "rarity": "Promo", "nationalPokedexNumbers": [863], "regulationMark": "D", "images": {"small": "https://images.pokemontcg.io/swshp/SWSH008.png", "large": "https://images.pokemontcg.io/swshp/SWSH008_hires.png"}}