{"id": "swsh10-3", "name": "Hisuian Electrode", "flavorText": "The tissue on the surface of its body is curiously similar in composition to an Apricorn. When irritated, this Pok\u00e9mon lets loose an electric current equal to 20 lightning bolts.", "types": ["Grass"], "supertype": "Pok\u00e9mon", "subtypes": ["Stage 1"], "hp": "90", "evolvesFrom": "Hisuian Voltorb", "attacks": [{"name": "Triple Draw", "cost": [], "convertedEnergyCost": 0, "damage": "", "text": "Draw 3 cards."}, {"name": "Irritated Bomb", "cost": [], "convertedEnergyCost": 0, "damage": "50", "text": ""}], "weaknesses": [{"type": "Fire", "value": "\u00d72"}], "retreatCost": ["Colorless"], "convertedRetreatCost": 1, "number": "3", "artist": "Akira Komayama", "rarity": "Uncommon", "nationalPokedexNumbers": [101], "regulationMark": "F", "images": {"small": "https://images.pokemontcg.io/swsh10/3.png", "large": "https://images.pokemontcg.io/swsh10/3_hires.png"}}