{"id": "neo1-50", "name": "Sunflora", "flavorText": "It converts sunlight into energy. In the darkness after sunset, it closes its petals and becomes still.", "types": ["Grass"], "supertype": "Pok\u00e9mon", "subtypes": ["Stage 1"], "level": "36", "hp": "70", "evolvesFrom": "Sunkern", "attacks": [{"name": "Petal Dance", "cost": ["Grass", "Grass", "Grass"], "convertedEnergyCost": 3, "damage": "30\u00d7", "text": "Flip 3 coins. This attack does 30 damage times the number of heads. Sunflora is now Confused (after doing damage)."}], "weaknesses": [{"type": "Fire", "value": "\u00d72"}], "retreatCost": ["Colorless"], "convertedRetreatCost": 1, "number": "50", "artist": "Kagemaru Himeno", "rarity": "Uncommon", "nationalPokedexNumbers": [192], "images": {"small": "https://images.pokemontcg.io/neo1/50.png", "large": "https://images.pokemontcg.io/neo1/50_hires.png"}}