{"id": "neo2-31", "name": "Tyranitar", "flavorText": "Its body can't be harmed by any sort of attack, so it is very eager to make challenges against enemies.", "types": ["Darkness"], "supertype": "Pok\u00e9mon", "subtypes": ["Stage 2"], "level": "54", "hp": "100", "evolvesFrom": "Pupitar", "attacks": [{"name": "Slam", "cost": ["Colorless", "Colorless", "Colorless"], "convertedEnergyCost": 3, "damage": "30\u00d7", "text": "Flip 2 coins. This attack does 30 damage times the number of heads."}, {"name": "Trample", "cost": ["Darkness", "Darkness", "Colorless", "Colorless"], "convertedEnergyCost": 4, "damage": "50", "text": "For each Benched Pok\u00e9mon in play (yours and your opponent's), flip a coin. If heads, this attack does 30 damage to that Pok\u00e9mon. (Don't apply Weakness and Resistance for Benched Pok\u00e9mon.)"}], "resistances": [{"type": "Psychic", "value": "-30"}], "retreatCost": ["Colorless", "Colorless", "Colorless"], "convertedRetreatCost": 3, "number": "31", "artist": "Hironobu Yoshida", "rarity": "Rare", "nationalPokedexNumbers": [248], "images": {"small": "https://images.pokemontcg.io/neo2/31.png", "large": "https://images.pokemontcg.io/neo2/31_hires.png"}}